mfcqi/__init__.py
mfcqi/__main__.py
mfcqi/calculator.py
mfcqi/py.typed
mfcqi/quality_gates.py
mfcqi/analysis/__init__.py
mfcqi/analysis/config.py
mfcqi/analysis/diagnostics.py
mfcqi/analysis/engine.py
mfcqi/analysis/tools/__init__.py
mfcqi/analysis/tools/bandit_analyzer.py
mfcqi/analysis/tools/detect_secrets_analyzer.py
mfcqi/analysis/tools/pip_audit_analyzer.py
mfcqi/analysis/tools/pylint_analyzer.py
mfcqi/analysis/tools/ruff_analyzer.py
mfcqi/cli/__init__.py
mfcqi/cli/main.py
mfcqi/cli/commands/__init__.py
mfcqi/cli/commands/analyze.py
mfcqi/cli/commands/analyze_helpers.py
mfcqi/cli/commands/badge.py
mfcqi/cli/commands/badge_templates.py
mfcqi/cli/commands/config.py
mfcqi/cli/commands/models.py
mfcqi/cli/utils/__init__.py
mfcqi/cli/utils/config_manager.py
mfcqi/cli/utils/llm_handler.py
mfcqi/cli/utils/output.py
mfcqi/core/__init__.py
mfcqi/core/file_utils.py
mfcqi/core/metric.py
mfcqi/core/paradigm_detector.py
mfcqi/metrics/__init__.py
mfcqi/metrics/code_smell.py
mfcqi/metrics/cognitive.py
mfcqi/metrics/cohesion.py
mfcqi/metrics/complexity.py
mfcqi/metrics/coupling.py
mfcqi/metrics/dependency_security.py
mfcqi/metrics/dit.py
mfcqi/metrics/documentation.py
mfcqi/metrics/duplication.py
mfcqi/metrics/maintainability.py
mfcqi/metrics/mhf.py
mfcqi/metrics/rfc.py
mfcqi/metrics/secrets_exposure.py
mfcqi/metrics/security.py
mfcqi/metrics/type_safety.py
mfcqi/smell_detection/__init__.py
mfcqi/smell_detection/aggregator.py
mfcqi/smell_detection/ast_test_smells.py
mfcqi/smell_detection/detector_base.py
mfcqi/smell_detection/models.py
mfcqi/smell_detection/pyexamine.py
mfcqi/templates/code_quality_analysis.j2
mfcqi/templates/fallback_recommendations.j2
mfcqi-0.0.2.dist-info/METADATA
mfcqi-0.0.2.dist-info/WHEEL
mfcqi-0.0.2.dist-info/entry_points.txt
mfcqi-0.0.2.dist-info/licenses/LICENSE
mfcqi-0.0.2.dist-info/RECORD
