Metadata-Version: 2.4
Name: mfcqi
Version: 0.0.2
Summary: MFCQI - Benchmark Analysis Reporting Utility for comprehensive code quality analysis with LLM integration
Project-URL: Homepage, https://github.com/bsbodden/mfcqi
Project-URL: Bug Reports, https://github.com/bsbodden/mfcqi/issues
Project-URL: Source, https://github.com/bsbodden/mfcqi
Project-URL: Documentation, https://mfcqi.readthedocs.io/
Author-email: Brian Sam-Bodden <bsbodden@gmail.com>
Maintainer-email: Brian Sam-Bodden <bsbodden@gmail.com>
License: MIT
License-File: LICENSE
Keywords: ai,code-analysis,code-quality,llm,metrics,quality-assurance,static-analysis,tdd,testing
Classifier: Development Status :: 4 - Beta
Classifier: Environment :: Console
Classifier: Intended Audience :: Developers
Classifier: License :: OSI Approved :: MIT License
Classifier: Operating System :: OS Independent
Classifier: Programming Language :: Python :: 3
Classifier: Programming Language :: Python :: 3.10
Classifier: Programming Language :: Python :: 3.11
Classifier: Programming Language :: Python :: 3.12
Classifier: Programming Language :: Python :: 3.13
Classifier: Topic :: Scientific/Engineering :: Artificial Intelligence
Classifier: Topic :: Software Development :: Libraries :: Python Modules
Classifier: Topic :: Software Development :: Quality Assurance
Classifier: Topic :: Software Development :: Testing
Classifier: Typing :: Typed
Requires-Python: >=3.10
Requires-Dist: bandit>=1.8.6
Requires-Dist: click>=8.0.0
Requires-Dist: cognitive-complexity>=1.3.0
Requires-Dist: detect-secrets>=1.5.0
Requires-Dist: jinja2>=3.1.2
Requires-Dist: keyring>=24.0.0
Requires-Dist: litellm>=1.77.3
Requires-Dist: pip-audit>=2.7.0
Requires-Dist: pydantic>=2.11.9
Requires-Dist: pylint>=3.3.8
Requires-Dist: pyyaml>=6.0.0
Requires-Dist: radon>=6.0.1
Requires-Dist: requests>=2.31.0
Requires-Dist: rich>=13.0.0
Requires-Dist: toml>=0.10.2
